nornir_inspect.py
nornir_inspect-1.1.1.dist-info/METADATA
nornir_inspect-1.1.1.dist-info/WHEEL
nornir_inspect-1.1.1.dist-info/licenses/LICENSE
nornir_inspect-1.1.1.dist-info/RECORD
