Metadata-Version: 2.4
Name: nornir-inspect
Version: 1.1.1
Summary: Nornir inspection tool
Author-email: Packet Coders <contact@packetcoders.io>
License-File: LICENSE
Requires-Python: ~=3.11
Requires-Dist: nornir<4,>=3.5.0
Requires-Dist: rich<15,>=12
